INSTALL
LICENSE
MANIFEST.in
README.md
setup.cfg
setup.py
fdfs_client/__init__.py
fdfs_client/cli.py
fdfs_client/client.py
fdfs_client/connection.py
fdfs_client/exceptions.py
fdfs_client/fdfs_protol.py
fdfs_client/fdfs_test.py
fdfs_client/file_crypt.py
fdfs_client/jsonencoder.py
fdfs_client/storage_client.py
fdfs_client/tracker_client.py
fdfs_client/utils.py
py3fdfsv2.egg-info/PKG-INFO
py3fdfsv2.egg-info/SOURCES.txt
py3fdfsv2.egg-info/dependency_links.txt
py3fdfsv2.egg-info/entry_points.txt
py3fdfsv2.egg-info/requires.txt
py3fdfsv2.egg-info/top_level.txt
test/test_config_file.py
test/test_file_info.py
test/test_file_regenrate_appender_name.py