Metadata-Version: 2.1
Name: py3fdfsv2
Version: 2.4.1
Summary: Python client for Fastdfs ver 4.06
Home-page: UNKNOWN
Author: scott yuan
Author-email: scottzer8@gmail.com
Maintainer: Jian Dai
Maintainer-email: daijian1@qq.com
License: GPLV3
Keywords: Fastdfs,Distribute File System
Platform: UNKNOWN
Classifier: Development Status :: 4 - Beta
Classifier: Programming Language :: Python :: 3
Classifier: License :: OSI Approved :: GNU General Public License v3 (GPLv3)
Classifier: Programming Language :: Python
